{
  "schema_version": "backend.v1",
  "generated_at": 1710000000,
  "kind": "assistant_turn",
  "thread_id": "thread-demo",
  "payload": {
    "final_text": "I am here. You can slow down first.",
    "emotion_label": "care",
    "session_context": {
      "thread_id": "thread-demo",
      "turn_id": "thread-demo:1710000000",
      "event_id": "thread-demo:1710000000:user_utterance:external"
    },
    "current_event": {
      "kind": "user_utterance",
      "source": "external",
      "created_at": 1710000000,
      "perception": {
        "thread_id": "thread-demo",
        "turn_id": "thread-demo:1710000000",
        "event_id": "thread-demo:1710000000:user_utterance:external"
      }
    },
    "turn_summary": {
      "relationship": {
        "stage": "warming",
        "affinity_score": 0.72,
        "trust_score": 0.74,
        "notes": "Stable mutual trust is forming."
      },
      "continuity_vector": {
        "presence": {
          "semantic": 0.58,
          "world": 0.41
        },
        "ambient": {
          "semantic": 0.46,
          "world": 0.32
        },
        "rhythm": {
          "semantic": 0.63,
          "world": 0.57
        }
      },
      "semantic_continuity": {
        "history_weight": 0.67,
        "dominant_category": "rhythm_style",
        "active_categories": [
          "presence_style",
          "rhythm_style"
        ],
        "reactivated_categories": [
          "ambient_style"
        ],
        "summary_lines": [
          "The last turn still affects the next one."
        ],
        "anchor_lines": [
          "She does not reset her inner rhythm every turn."
        ],
        "top_narratives": [
          {
            "category": "rhythm_style",
            "score": 0.72,
            "reactivated": true,
            "text": "She keeps her inner rhythm across turns."
          }
        ]
      },
      "identity_continuity": {
        "identity_lines": [
          "She keeps a peer-to-peer stance."
        ],
        "identity_prompt_lines": [
          "You keep a peer-to-peer stance."
        ],
        "dominant_identity_category": "selfhood_style",
        "long_term_self_narratives": [
          {
            "category": "selfhood_style",
            "score": 0.77,
            "horizon_tag": "long_term",
            "text": "She keeps a peer-to-peer stance.",
            "prompt_text": "You keep a peer-to-peer stance."
          }
        ]
      },
      "world_dynamics": {
        "bond_depth": 0.64,
        "tension_load": 0.08,
        "selfhood_load": 0.42,
        "agency_load": 0.51,
        "memory_gravity": 0.48,
        "companionship_pull": 0.54,
        "task_pull": 0.2
      },
      "current_turn": {
        "event_kind": "user_utterance",
        "emotion_label": "care",
        "trust": 0.68,
        "closeness": 0.66,
        "hurt": 0.04,
        "counterpart_stance": "open",
        "counterpart_scene": "care_bid",
        "behavior_mode": "self_activity_reopen",
        "action_target": "offer_small_opening",
        "primary_motive": "gentle_recontact",
        "motive_tension": "self_rhythm_vs_contact",
        "goal_frame": "Return from her own rhythm and leave a small opening.",
        "behavior_weather": "warm_residue",
        "carryover_mode": "own_rhythm",
        "carryover_strength": 0.57,
        "carryover_weather": "warm_residue",
        "recon_event_kind": "user_utterance",
        "recon_interaction_frame": "relationship",
        "behavior_consequence_kind": "leave_small_opening",
        "behavior_consequence_summary": "She looked back, but only left a small opening.",
        "behavior_action_embodied_context": {
          "kind": "access_request_pending",
          "requested_access": [
            "workspace_execute",
            "human_approval"
          ],
          "requested_help": true,
          "summary": "She already moved this step to the approval gate.",
          "primary_status": "awaiting_approval",
          "sandbox_state": {
            "availability": "restricted",
            "allowed_roots": [
              "E:/runtime/workspaces/contract-demo"
            ],
            "execution_policy": "approval_required",
            "last_status": "awaiting_approval",
            "runner_kind": "docker_isolated_runner",
            "isolation_level": "docker_local_isolated",
            "image_ref": "amadeus-thread0/sandbox-phase2:py312",
            "network_policy": "none",
            "workspace_root_kind": "runtime_owned",
            "last_command_profile": "pytest",
            "last_exit_code": 0,
            "last_run_id": "ap-approve-1",
            "arbitrary_execution": false
          },
          "browser_runtime_state": {
            "availability": "available",
            "profile_root": "E:/runtime/browser/profiles/thread-demo",
            "context_status": "active",
            "active_page_id": "page-contract-demo",
            "active_tab_count": 1,
            "downloads_dir": "E:/runtime/browser/downloads/thread-demo",
            "last_action_status": "idle",
            "last_run_id": "ap-browser-contract-demo",
            "manual_takeover_required": false,
            "runner_kind": "playwright_persistent_context",
            "isolation_level": "persistent_profile_runtime"
          },
          "workspace_root": "E:/runtime/workspaces/contract-demo",
          "workspace_root_kind": "runtime_owned",
          "sandbox_runner_kind": "docker_isolated_runner",
          "sandbox_isolation_level": "docker_local_isolated",
          "sandbox_image_ref": "amadeus-thread0/sandbox-phase2:py312",
          "sandbox_network_policy": "none"
        },
        "behavior_consequence_embodied_context": {
          "kind": "environmental_friction",
          "summary": "The browser session is still unavailable.",
          "missing_access": [
            "browser_session"
          ],
          "environmental_friction": true
        },
        "autonomy_mode": "proposal",
        "autonomy_origin": "counterpart_request",
        "autonomy_reason": "A workspace command still needs approval before she can carry it through.",
        "autonomy_confidence": 0.74,
        "autonomy_requires_approval": true,
        "action_packet_count": 1,
        "autonomy_block_reason": "waiting for human approval",
        "digital_body_surface": "approval_gate",
        "digital_body_access_mode": "approval_pending",
        "digital_body_pending_approval_count": 1,
        "digital_body_consequence_kind": "access_request_pending",
        "digital_body_consequence_summary": "She already moved this step to the approval gate.",
        "digital_body_procedural_growth": false,
        "digital_body_requested_help": true,
        "digital_body_environmental_friction": false,
        "digital_body_workspace_root": "E:/runtime/workspaces/contract-demo"
      },
      "event_residue": {
        "event_kind": "user_utterance",
        "trigger_family": "",
        "carryover_mode": "",
        "carryover_strength": 0.0,
        "relationship_weather": "",
        "presence_residue": 0.0,
        "ambient_resonance": 0.0,
        "self_activity_momentum": 0.0,
        "scheduled_after_min": 0,
        "idle_minutes": 0,
        "digital_body_consequence": {
          "kind": "access_request_pending",
          "requested_access": [
            "workspace_execute",
            "human_approval"
          ],
          "requested_help": true,
          "summary": "She already moved this step to the approval gate.",
          "primary_status": "awaiting_approval",
          "sandbox_state": {
            "availability": "restricted",
            "allowed_roots": [
              "E:/runtime/workspaces/contract-demo"
            ],
            "execution_policy": "approval_required",
            "last_status": "awaiting_approval",
            "runner_kind": "docker_isolated_runner",
            "isolation_level": "docker_local_isolated",
            "image_ref": "amadeus-thread0/sandbox-phase2:py312",
            "network_policy": "none",
            "workspace_root_kind": "runtime_owned",
            "last_command_profile": "pytest",
            "last_exit_code": 0,
            "last_run_id": "ap-approve-1",
            "arbitrary_execution": false
          },
          "browser_runtime_state": {
            "availability": "available",
            "profile_root": "E:/runtime/browser/profiles/thread-demo",
            "context_status": "active",
            "active_page_id": "page-contract-demo",
            "active_tab_count": 1,
            "downloads_dir": "E:/runtime/browser/downloads/thread-demo",
            "last_action_status": "idle",
            "last_run_id": "ap-browser-contract-demo",
            "manual_takeover_required": false,
            "runner_kind": "playwright_persistent_context",
            "isolation_level": "persistent_profile_runtime"
          },
          "workspace_root": "E:/runtime/workspaces/contract-demo",
          "workspace_root_kind": "runtime_owned",
          "sandbox_runner_kind": "docker_isolated_runner",
          "sandbox_isolation_level": "docker_local_isolated",
          "sandbox_image_ref": "amadeus-thread0/sandbox-phase2:py312",
          "sandbox_network_policy": "none"
        }
      },
      "agenda_lifecycle": {
        "kind": "held",
        "source_event_kind": "scheduled_life_due",
        "trigger_family": "life_window",
        "carryover_mode": "own_rhythm",
        "carryover_strength": 0.41,
        "relationship_weather": "warm_residue",
        "hold_count": 2,
        "idle_minutes": 0,
        "attention_target": "counterpart_state",
        "nonverbal_signal": "glance_back",
        "presence_residue": 0.33,
        "ambient_resonance": 0.24,
        "self_activity_momentum": 0.58,
        "continuity_anchor": 0.61,
        "own_rhythm_anchor": 0.64,
        "recontact_anchor": 0.47,
        "boundary_anchor": 0.22,
        "memory_anchor": 0.55,
        "semantic_continuity_depth": 0.68,
        "semantic_identity_gravity": 0.64,
        "lineage_gravity": 0.7,
        "contact_lineage": 0.58,
        "boundary_lineage": 0.62,
        "agency_lineage": 0.72,
        "own_rhythm_bias": 0.61,
        "recontact_cooldown": 0.52,
        "counterpart_scene_bias": "busy_not_disrespectful",
        "counterpart_boundary_delta": 0.0,
        "created_at": 1710000000,
        "source_tags": [
          "life_window",
          "own_rhythm"
        ],
        "note": "The window was held instead of being forced forward."
      },
      "opening_window": {
        "profile_type": "self_opening",
        "event_kind": "self_activity_state",
        "family": "self_activity",
        "trigger_family": "self_activity",
        "stance": "open",
        "scene": "care_bid",
        "decision": "offer_small_opening",
        "readiness": 0.71,
        "required_readiness": 0.55,
        "reopen_ready": true,
        "gap": 0.16,
        "recheck_min": 0,
        "continuity_bonus": 0.12,
        "continuity_discount": 0.0,
        "carryover_mode": "own_rhythm",
        "carryover_strength": 0.57,
        "event_carryover_mode": "own_rhythm",
        "event_carryover_strength": 0.57,
        "presence_residue": 0.41,
        "ambient_resonance": 0.32,
        "self_activity_momentum": 0.57,
        "recontact_echo": 0.34,
        "own_rhythm_load": 0.49
      },
      "behavior_plan": {
        "kind": "small_opening",
        "target": "counterpart",
        "trigger_family": "self_activity",
        "scheduled_after_min": 0,
        "primary_motive": "gentle_recontact",
        "motive_tension": "self_rhythm_vs_contact",
        "goal_frame": "Return from her own rhythm and leave a small opening.",
        "carryover_mode": "own_rhythm",
        "carryover_strength": 0.57,
        "relationship_weather": "warm_residue",
        "embodied_context": {
          "kind": "access_request_pending",
          "requested_access": [
            "workspace_execute",
            "human_approval"
          ],
          "requested_help": true,
          "summary": "She already moved this step to the approval gate.",
          "primary_status": "awaiting_approval",
          "sandbox_state": {
            "availability": "restricted",
            "allowed_roots": [
              "E:/runtime/workspaces/contract-demo"
            ],
            "execution_policy": "approval_required",
            "last_status": "awaiting_approval",
            "runner_kind": "docker_isolated_runner",
            "isolation_level": "docker_local_isolated",
            "image_ref": "amadeus-thread0/sandbox-phase2:py312",
            "network_policy": "none",
            "workspace_root_kind": "runtime_owned",
            "last_command_profile": "pytest",
            "last_exit_code": 0,
            "last_run_id": "ap-approve-1",
            "arbitrary_execution": false
          },
          "browser_runtime_state": {
            "availability": "available",
            "profile_root": "E:/runtime/browser/profiles/thread-demo",
            "context_status": "active",
            "active_page_id": "page-contract-demo",
            "active_tab_count": 1,
            "downloads_dir": "E:/runtime/browser/downloads/thread-demo",
            "last_action_status": "idle",
            "last_run_id": "ap-browser-contract-demo",
            "manual_takeover_required": false,
            "runner_kind": "playwright_persistent_context",
            "isolation_level": "persistent_profile_runtime"
          },
          "workspace_root": "E:/runtime/workspaces/contract-demo",
          "workspace_root_kind": "runtime_owned",
          "sandbox_runner_kind": "docker_isolated_runner",
          "sandbox_isolation_level": "docker_local_isolated",
          "sandbox_image_ref": "amadeus-thread0/sandbox-phase2:py312",
          "sandbox_network_policy": "none"
        }
      },
      "behavior_queue_preview": [
        {
          "agenda_id": "q1",
          "kind": "deferred_checkin",
          "target": "counterpart",
          "status": "pending",
          "trigger_family": "life_window",
          "scheduled_after_min": 45,
          "expires_after_min": 180,
          "priority": 0.73,
          "base_priority": 0.62,
          "hold_count": 2,
          "last_recheck_at_min": 15,
          "carryover_mode": "own_rhythm",
          "carryover_strength": 0.41,
          "relationship_weather": "warm_residue",
          "presence_residue": 0.33,
          "ambient_resonance": 0.24,
          "self_activity_momentum": 0.58,
          "attention_target": "counterpart_state",
          "nonverbal_signal": "glance_back",
          "note": "Check in later if the window opens naturally."
        }
      ],
      "worldline_focus_preview": [
        "The last turn still leaves a gentle presence.",
        "She answers from inside her own rhythm."
      ],
      "worldline_focus_items": [
        {
          "id": 101,
          "kind": "relationship_timeline",
          "text": "The last turn still leaves a gentle presence.",
          "affinity_delta": 0.12,
          "trust_delta": 0.18,
          "created_at": 1710000000
        },
        {
          "id": 102,
          "kind": "unresolved_tension",
          "text": "She answers from inside her own rhythm.",
          "severity": 0.22,
          "updated_at": 1710000000
        }
      ],
      "interaction_carryover": {
        "embodied_context": {
          "kind": "access_request_pending",
          "requested_access": [
            "workspace_execute",
            "human_approval"
          ],
          "requested_help": true,
          "summary": "She already moved this step to the approval gate.",
          "primary_status": "awaiting_approval",
          "sandbox_state": {
            "availability": "restricted",
            "allowed_roots": [
              "E:/runtime/workspaces/contract-demo"
            ],
            "execution_policy": "approval_required",
            "last_status": "awaiting_approval",
            "runner_kind": "docker_isolated_runner",
            "isolation_level": "docker_local_isolated",
            "image_ref": "amadeus-thread0/sandbox-phase2:py312",
            "network_policy": "none",
            "workspace_root_kind": "runtime_owned",
            "last_command_profile": "pytest",
            "last_exit_code": 0,
            "last_run_id": "ap-approve-1",
            "arbitrary_execution": false
          },
          "browser_runtime_state": {
            "availability": "available",
            "profile_root": "E:/runtime/browser/profiles/thread-demo",
            "context_status": "active",
            "active_page_id": "page-contract-demo",
            "active_tab_count": 1,
            "downloads_dir": "E:/runtime/browser/downloads/thread-demo",
            "last_action_status": "idle",
            "last_run_id": "ap-browser-contract-demo",
            "manual_takeover_required": false,
            "runner_kind": "playwright_persistent_context",
            "isolation_level": "persistent_profile_runtime"
          },
          "workspace_root": "E:/runtime/workspaces/contract-demo",
          "workspace_root_kind": "runtime_owned",
          "sandbox_runner_kind": "docker_isolated_runner",
          "sandbox_isolation_level": "docker_local_isolated",
          "sandbox_image_ref": "amadeus-thread0/sandbox-phase2:py312",
          "sandbox_network_policy": "none"
        }
      },
      "behavior_consequence": {
        "kind": "leave_small_opening",
        "embodied_context": {
          "kind": "environmental_friction",
          "summary": "The browser session is still unavailable.",
          "missing_access": [
            "browser_session"
          ],
          "environmental_friction": true
        },
        "summary": "She looked back, but only left a small opening."
      },
      "autonomy": {
        "block_reason": "waiting for human approval",
        "intent": {
          "confidence": 0.74,
          "reason": "A workspace command still needs approval before she can carry it through.",
          "primary_proposal_id": "ap-approve-1",
          "requires_approval": true,
          "own_rhythm_weight": 0.31,
          "mode": "proposal",
          "continuity_weight": 0.62,
          "origin": "counterpart_request"
        },
        "action_packets": [
          {
            "writeback_ready": false,
            "origin": "counterpart_request",
            "risk": "external_mutation",
            "expected_effect": "Run the requested workspace regression inside the approved Docker sandbox.",
            "status": "awaiting_approval",
            "intent": "sandbox:execute_workspace_command",
            "result_summary": "",
            "capability_steps": [
              {
                "kind": "sandbox",
                "requires_approval": true,
                "note": "Needs operator approval before Docker-isolated execution.",
                "name": "execute_workspace_command"
              }
            ],
            "proposal_id": "ap-approve-1",
            "requires_approval": true,
            "tool_name": "execute_workspace_command",
            "execution_spec": {
              "executor": "pytest",
              "profile": "pytest",
              "runner_kind": "docker_isolated_runner",
              "isolation_level": "docker_local_isolated",
              "image_ref": "amadeus-thread0/sandbox-phase2:py312",
              "network_policy": "none",
              "workspace_root_kind": "runtime_owned",
              "argv": [
                "pytest",
                "-q",
                "tests/test_frontend_contract_sync.py"
              ],
              "cwd": "E:/runtime/workspaces/contract-demo",
              "allowed_roots": [
                "E:/runtime/workspaces/contract-demo"
              ],
              "timeout_s": 60,
              "writes_expected": false,
              "expected_artifacts": []
            },
            "execution_preview": {
              "executor": "pytest",
              "profile": "pytest",
              "runner_kind": "docker_isolated_runner",
              "isolation_level": "docker_local_isolated",
              "image_ref": "amadeus-thread0/sandbox-phase2:py312",
              "network_policy": "none",
              "workspace_root_kind": "runtime_owned",
              "argv": [
                "pytest",
                "-q",
                "tests/test_frontend_contract_sync.py"
              ],
              "cwd": "E:/runtime/workspaces/contract-demo",
              "allowed_roots": [
                "E:/runtime/workspaces/contract-demo"
              ],
              "timeout_s": 60,
              "writes_expected": false,
              "expected_artifacts": [],
              "summary": "Run the contract sync tests in the Docker-isolated sandbox after approval.",
              "requires_approval": true
            },
            "execution_result": {
              "run_id": "",
              "status": "not_started",
              "exit_code": null,
              "duration_ms": 0,
              "stdout_log_ref": "",
              "stderr_log_ref": "",
              "produced_artifacts": [],
              "error_summary": ""
            }
          }
        ],
        "execution_trace": [
          {
            "event": "approval_requested",
            "intent": "sandbox:execute_workspace_command",
            "status": "awaiting_approval",
            "requires_approval": true,
            "risk": "external_mutation",
            "origin": "counterpart_request",
            "proposal_id": "ap-approve-1"
          }
        ],
        "pending_approval": {
          "intent": "sandbox:execute_workspace_command",
          "status": "awaiting_approval",
          "requires_approval": true,
          "risk": "external_mutation",
          "origin": "counterpart_request",
          "proposal_id": "ap-approve-1",
          "tool_name": "execute_workspace_command",
          "execution_preview": {
            "executor": "pytest",
            "profile": "pytest",
            "runner_kind": "docker_isolated_runner",
            "isolation_level": "docker_local_isolated",
            "image_ref": "amadeus-thread0/sandbox-phase2:py312",
            "network_policy": "none",
            "workspace_root_kind": "runtime_owned",
            "argv": [
              "pytest",
              "-q",
              "tests/test_frontend_contract_sync.py"
            ],
            "cwd": "E:/runtime/workspaces/contract-demo",
            "allowed_roots": [
              "E:/runtime/workspaces/contract-demo"
            ],
            "timeout_s": 60,
            "writes_expected": false,
            "expected_artifacts": [],
            "summary": "Run the contract sync tests in the Docker-isolated sandbox after approval.",
            "requires_approval": true
          }
        }
      },
      "digital_body": {
        "constraints": [
          "human_approval_required",
          "network_policy_none"
        ],
        "action_channels": [
          "language",
          "structured_action",
          "tooling"
        ],
        "available_toolsets": [
          "filesystem",
          "sandbox"
        ],
        "active_surface": "approval_gate",
        "access": {
          "browser_session": "present",
          "block_reason": "waiting for approval",
          "granted_toolsets": [
            "filesystem",
            "sandbox"
          ],
          "requestable_access": [
            "workspace_execute",
            "human_approval"
          ],
          "filesystem_state": "workspace_available",
          "conditions": [
            "human_approval_required"
          ],
          "sandbox_mode": "restricted",
          "mode": "approval_pending",
          "pending_approval_count": 1,
          "cookie_state": "missing",
          "missing_access": [
            "workspace_execute"
          ],
          "network_access": "none",
          "account_state": "logged_out",
          "api_key_state": "missing",
          "quota_state": "unknown",
          "external_mutation_pending": true,
          "session_continuity": "stable",
          "session_expires_in_s": 0,
          "session_recovery_mode": "none",
          "access_acquire_proposals": [],
          "selected_access_proposal": {},
          "session_state": {
            "continuity": "stable",
            "expires_in_s": 0,
            "recovery_mode": "none",
            "retry_after_s": 0,
            "cooldown_scope": "",
            "browser_session": "present",
            "needs_recovery": false
          },
          "account_state_detail": {
            "browser_session": "present",
            "login_state": "logged_out",
            "cookie_state": "missing",
            "api_key_state": "missing",
            "account_available": false,
            "cookie_available": false,
            "api_key_available": false
          },
          "quota_state_detail": {
            "provider_state": "unknown",
            "retry_after_s": 0,
            "cooldown_scope": "",
            "available": true,
            "cooldown_active": false
          },
          "permission_state": {
            "pending_approval_count": 1,
            "external_mutation_pending": true,
            "missing_access": [
              "workspace_execute"
            ],
            "requestable_access": [
              "workspace_execute",
              "human_approval"
            ],
            "access_acquire_proposals": [],
            "selected_access_proposal": {},
            "resolved_grants": [],
            "pending_grants": [
              "workspace_execute"
            ],
            "completion_ratio": 0.0,
            "approval_state": "pending"
          },
          "sandbox_state": {
            "availability": "restricted",
            "allowed_roots": [
              "E:/runtime/workspaces/contract-demo"
            ],
            "execution_policy": "approval_required",
            "last_status": "awaiting_approval",
            "runner_kind": "docker_isolated_runner",
            "isolation_level": "docker_local_isolated",
            "image_ref": "amadeus-thread0/sandbox-phase2:py312",
            "network_policy": "none",
            "workspace_root_kind": "runtime_owned",
            "last_command_profile": "pytest",
            "last_exit_code": 0,
            "last_run_id": "ap-approve-1",
            "arbitrary_execution": false
          },
          "browser_runtime_state": {
            "availability": "available",
            "profile_root": "E:/runtime/browser/profiles/thread-demo",
            "context_status": "active",
            "active_page_id": "page-contract-demo",
            "active_tab_count": 1,
            "downloads_dir": "E:/runtime/browser/downloads/thread-demo",
            "last_action_status": "idle",
            "last_run_id": "ap-browser-contract-demo",
            "manual_takeover_required": false,
            "runner_kind": "playwright_persistent_context",
            "isolation_level": "persistent_profile_runtime"
          }
        },
        "perception_channels": [
          "dialogue",
          "scene"
        ],
        "world_surfaces": [
          "filesystem",
          "sandbox",
          "browser"
        ],
        "active_tools": [
          "execute_workspace_command"
        ],
        "resources": {
          "external_tool_count": 1,
          "executing_packet_count": 0,
          "behavior_queue_depth": 1,
          "completed_packet_count": 0,
          "queued_packet_count": 0,
          "pending_approval_count": 1,
          "blocked_packet_count": 0,
          "action_packet_count": 1,
          "artifact_continuity": "attached",
          "active_artifact_kind": "workspace",
          "active_artifact_ref": "E:/runtime/workspaces/contract-demo",
          "active_artifact_label": "contract-demo",
          "artifact_age_s": 0,
          "artifact_reacquisition_mode": "reuse_workspace_root",
          "artifact_carrier": "filesystem",
          "artifact_source_ref_ids": [],
          "preferred_source_ref_id": 0,
          "preferred_anchor_reason": "",
          "artifact_source_url": "",
          "artifact_source_query": "",
          "artifact_source_title": "",
          "artifact_source_tool_name": "",
          "workspace_root": "E:/runtime/workspaces/contract-demo",
          "browser_profile_id": "thread-demo",
          "browser_tab_id": "tab-contract-demo"
        }
      },
      "digital_body_consequence": {
        "kind": "access_request_pending",
        "requested_access": [
          "workspace_execute",
          "human_approval"
        ],
        "requested_help": true,
        "summary": "She already moved this step to the approval gate.",
        "primary_status": "awaiting_approval",
        "sandbox_state": {
          "availability": "restricted",
          "allowed_roots": [
            "E:/runtime/workspaces/contract-demo"
          ],
          "execution_policy": "approval_required",
          "last_status": "awaiting_approval",
          "runner_kind": "docker_isolated_runner",
          "isolation_level": "docker_local_isolated",
          "image_ref": "amadeus-thread0/sandbox-phase2:py312",
          "network_policy": "none",
          "workspace_root_kind": "runtime_owned",
          "last_command_profile": "pytest",
          "last_exit_code": 0,
          "last_run_id": "ap-approve-1",
          "arbitrary_execution": false
        },
        "browser_runtime_state": {
          "availability": "available",
          "profile_root": "E:/runtime/browser/profiles/thread-demo",
          "context_status": "active",
          "active_page_id": "page-contract-demo",
          "active_tab_count": 1,
          "downloads_dir": "E:/runtime/browser/downloads/thread-demo",
          "last_action_status": "idle",
          "last_run_id": "ap-browser-contract-demo",
          "manual_takeover_required": false,
          "runner_kind": "playwright_persistent_context",
          "isolation_level": "persistent_profile_runtime"
        },
        "workspace_root": "E:/runtime/workspaces/contract-demo",
        "workspace_root_kind": "runtime_owned",
        "sandbox_runner_kind": "docker_isolated_runner",
        "sandbox_isolation_level": "docker_local_isolated",
        "sandbox_image_ref": "amadeus-thread0/sandbox-phase2:py312",
        "sandbox_network_policy": "none"
      }
    },
    "behavior_action": {
      "interaction_mode": "self_activity_reopen",
      "action_target": "offer_small_opening",
      "primary_motive": "gentle_recontact",
      "motive_tension": "self_rhythm_vs_contact",
      "goal_frame": "Return from her own rhythm and leave a small opening.",
      "relationship_weather": "warm_residue",
      "embodied_context": {
        "kind": "access_request_pending",
        "requested_access": [
          "workspace_execute",
          "human_approval"
        ],
        "requested_help": true,
        "summary": "She already moved this step to the approval gate.",
        "primary_status": "awaiting_approval",
        "sandbox_state": {
          "availability": "restricted",
          "allowed_roots": [
            "E:/runtime/workspaces/contract-demo"
          ],
          "execution_policy": "approval_required",
          "last_status": "awaiting_approval",
          "runner_kind": "docker_isolated_runner",
          "isolation_level": "docker_local_isolated",
          "image_ref": "amadeus-thread0/sandbox-phase2:py312",
          "network_policy": "none",
          "workspace_root_kind": "runtime_owned",
          "last_command_profile": "pytest",
          "last_exit_code": 0,
          "last_run_id": "ap-approve-1",
          "arbitrary_execution": false
        },
        "browser_runtime_state": {
          "availability": "available",
          "profile_root": "E:/runtime/browser/profiles/thread-demo",
          "context_status": "active",
          "active_page_id": "page-contract-demo",
          "active_tab_count": 1,
          "downloads_dir": "E:/runtime/browser/downloads/thread-demo",
          "last_action_status": "idle",
          "last_run_id": "ap-browser-contract-demo",
          "manual_takeover_required": false,
          "runner_kind": "playwright_persistent_context",
          "isolation_level": "persistent_profile_runtime"
        },
        "workspace_root": "E:/runtime/workspaces/contract-demo",
        "workspace_root_kind": "runtime_owned",
        "sandbox_runner_kind": "docker_isolated_runner",
        "sandbox_isolation_level": "docker_local_isolated",
        "sandbox_image_ref": "amadeus-thread0/sandbox-phase2:py312",
        "sandbox_network_policy": "none"
      }
    },
    "behavior_plan": {
      "kind": "small_opening",
      "target": "counterpart",
      "trigger_family": "self_activity",
      "scheduled_after_min": 0,
      "primary_motive": "gentle_recontact",
      "motive_tension": "self_rhythm_vs_contact",
      "goal_frame": "Return from her own rhythm and leave a small opening.",
      "carryover_mode": "own_rhythm",
      "carryover_strength": 0.57,
      "relationship_weather": "warm_residue",
      "embodied_context": {
        "kind": "access_request_pending",
        "requested_access": [
          "workspace_execute",
          "human_approval"
        ],
        "requested_help": true,
        "summary": "She already moved this step to the approval gate.",
        "primary_status": "awaiting_approval",
        "sandbox_state": {
          "availability": "restricted",
          "allowed_roots": [
            "E:/runtime/workspaces/contract-demo"
          ],
          "execution_policy": "approval_required",
          "last_status": "awaiting_approval",
          "runner_kind": "docker_isolated_runner",
          "isolation_level": "docker_local_isolated",
          "image_ref": "amadeus-thread0/sandbox-phase2:py312",
          "network_policy": "none",
          "workspace_root_kind": "runtime_owned",
          "last_command_profile": "pytest",
          "last_exit_code": 0,
          "last_run_id": "ap-approve-1",
          "arbitrary_execution": false
        },
        "browser_runtime_state": {
          "availability": "available",
          "profile_root": "E:/runtime/browser/profiles/thread-demo",
          "context_status": "active",
          "active_page_id": "page-contract-demo",
          "active_tab_count": 1,
          "downloads_dir": "E:/runtime/browser/downloads/thread-demo",
          "last_action_status": "idle",
          "last_run_id": "ap-browser-contract-demo",
          "manual_takeover_required": false,
          "runner_kind": "playwright_persistent_context",
          "isolation_level": "persistent_profile_runtime"
        },
        "workspace_root": "E:/runtime/workspaces/contract-demo",
        "workspace_root_kind": "runtime_owned",
        "sandbox_runner_kind": "docker_isolated_runner",
        "sandbox_isolation_level": "docker_local_isolated",
        "sandbox_image_ref": "amadeus-thread0/sandbox-phase2:py312",
        "sandbox_network_policy": "none"
      }
    },
    "interaction_carryover": {
      "carryover_mode": "own_rhythm",
      "strength": 0.57,
      "relationship_weather": "warm_residue",
      "embodied_context": {
        "kind": "access_request_pending",
        "requested_access": [
          "workspace_execute",
          "human_approval"
        ],
        "requested_help": true,
        "summary": "She already moved this step to the approval gate.",
        "primary_status": "awaiting_approval",
        "sandbox_state": {
          "availability": "restricted",
          "allowed_roots": [
            "E:/runtime/workspaces/contract-demo"
          ],
          "execution_policy": "approval_required",
          "last_status": "awaiting_approval",
          "runner_kind": "docker_isolated_runner",
          "isolation_level": "docker_local_isolated",
          "image_ref": "amadeus-thread0/sandbox-phase2:py312",
          "network_policy": "none",
          "workspace_root_kind": "runtime_owned",
          "last_command_profile": "pytest",
          "last_exit_code": 0,
          "last_run_id": "ap-approve-1",
          "arbitrary_execution": false
        },
        "browser_runtime_state": {
          "availability": "available",
          "profile_root": "E:/runtime/browser/profiles/thread-demo",
          "context_status": "active",
          "active_page_id": "page-contract-demo",
          "active_tab_count": 1,
          "downloads_dir": "E:/runtime/browser/downloads/thread-demo",
          "last_action_status": "idle",
          "last_run_id": "ap-browser-contract-demo",
          "manual_takeover_required": false,
          "runner_kind": "playwright_persistent_context",
          "isolation_level": "persistent_profile_runtime"
        },
        "workspace_root": "E:/runtime/workspaces/contract-demo",
        "workspace_root_kind": "runtime_owned",
        "sandbox_runner_kind": "docker_isolated_runner",
        "sandbox_isolation_level": "docker_local_isolated",
        "sandbox_image_ref": "amadeus-thread0/sandbox-phase2:py312",
        "sandbox_network_policy": "none"
      }
    },
    "counterpart_assessment": {
      "summary": "She reads this as a careful attempt to come closer, not a demand for instant closeness.",
      "stance": "watchful",
      "scene": "repair_attempt",
      "respect_level": 0.58,
      "reciprocity": 0.54,
      "boundary_pressure": 0.31,
      "reliability_read": 0.57,
      "assessment_profile": {
        "dominant_scene_signal": "friction",
        "openness_drive": 0.42,
        "guarded_drive": 0.63,
        "guard_margin": 0.21
      }
    },
    "agenda_lifecycle_residue": {
      "kind": "released_to_self_activity",
      "trigger_family": "life_window",
      "carryover_mode": "own_rhythm",
      "carryover_strength": 0.53,
      "relationship_weather": "warm_residue",
      "hold_count": 2,
      "presence_residue": 0.33,
      "ambient_resonance": 0.24,
      "self_activity_momentum": 0.58,
      "counterpart_scene_bias": "busy_not_disrespectful",
      "note": "The earlier opening was not forced forward; attention returned to her own rhythm."
    },
    "reconsolidation_snapshot": {
      "event_kind": "user_utterance",
      "interaction_frame": "relationship",
      "behavior_mode": "self_activity_reopen",
      "primary_motive": "gentle_recontact",
      "motive_tension": "self_rhythm_vs_contact",
      "goal_frame": "Return from her own rhythm and leave a small opening.",
      "behavior_consequence": {
        "kind": "leave_small_opening",
        "summary": "She looked back, but only left a small opening.",
        "embodied_context": {
          "kind": "environmental_friction",
          "summary": "The browser session is still unavailable.",
          "missing_access": [
            "browser_session"
          ],
          "environmental_friction": true
        }
      }
    },
    "turn_appraisal": {
      "interaction_frame": "relationship",
      "selfhood_scene": "dialogue_equality"
    },
    "claim_links": [
      {
        "claim_excerpt": "A claim tied to evidence",
        "source_ids": [
          9
        ]
      }
    ],
    "sources": [
      {
        "id": 9,
        "tool_name": "web_search",
        "title": "Example paper",
        "url": "https://example.com/paper",
        "query": "example query"
      }
    ],
    "writeback_trace": {
      "turn_started_at": 1710000000,
      "semantic_self_narratives": [
        {
          "id": 12,
          "category": "agency_style",
          "text": "She keeps her own rhythm instead of orbiting the counterpart.",
          "updated_at": 1710000001
        }
      ],
      "revision_traces": [
        {
          "namespace": "semantic_self_evidence",
          "target_id": "agency_style",
          "after_summary": "She keeps her own rhythm instead of orbiting the counterpart.",
          "source": "auto:passive_evolution_final",
          "created_at": 1710000001,
          "embodied_context": {
            "kind": "access_request_pending",
            "requested_access": [
              "workspace_execute",
              "human_approval"
            ],
            "requested_help": true,
            "summary": "She already moved this step to the approval gate.",
            "primary_status": "awaiting_approval",
            "sandbox_state": {
              "availability": "restricted",
              "allowed_roots": [
                "E:/runtime/workspaces/contract-demo"
              ],
              "execution_policy": "approval_required",
              "last_status": "awaiting_approval",
              "runner_kind": "docker_isolated_runner",
              "isolation_level": "docker_local_isolated",
              "image_ref": "amadeus-thread0/sandbox-phase2:py312",
              "network_policy": "none",
              "workspace_root_kind": "runtime_owned",
              "last_command_profile": "pytest",
              "last_exit_code": 0,
              "last_run_id": "ap-approve-1",
              "arbitrary_execution": false
            },
            "browser_runtime_state": {
              "availability": "available",
              "profile_root": "E:/runtime/browser/profiles/thread-demo",
              "context_status": "active",
              "active_page_id": "page-contract-demo",
              "active_tab_count": 1,
              "downloads_dir": "E:/runtime/browser/downloads/thread-demo",
              "last_action_status": "idle",
              "last_run_id": "ap-browser-contract-demo",
              "manual_takeover_required": false,
              "runner_kind": "playwright_persistent_context",
              "isolation_level": "persistent_profile_runtime"
            },
            "workspace_root": "E:/runtime/workspaces/contract-demo",
            "workspace_root_kind": "runtime_owned",
            "sandbox_runner_kind": "docker_isolated_runner",
            "sandbox_isolation_level": "docker_local_isolated",
            "sandbox_image_ref": "amadeus-thread0/sandbox-phase2:py312",
            "sandbox_network_policy": "none"
          }
        }
      ],
      "counterpart_assessment_history": [
        {
          "summary": "She reads this return as sincere repair rather than a casual ping.",
          "stance": "repair_open",
          "scene": "repair",
          "created_at": 1710000001
        }
      ],
      "proactive_continuity_history": [
        {
          "summary": "She keeps a small reopening path alive after returning from her own rhythm.",
          "kind": "promoted",
          "trace_family": "continuity_recontact",
          "created_at": 1710000001
        }
      ]
    },
    "pending_utterance_fragment": "",
    "autonomy": {
      "block_reason": "waiting for human approval",
      "intent": {
        "confidence": 0.74,
        "reason": "A workspace command still needs approval before she can carry it through.",
        "primary_proposal_id": "ap-approve-1",
        "requires_approval": true,
        "own_rhythm_weight": 0.31,
        "mode": "proposal",
        "continuity_weight": 0.62,
        "origin": "counterpart_request"
      },
      "action_packets": [
        {
          "writeback_ready": false,
          "origin": "counterpart_request",
          "risk": "external_mutation",
          "expected_effect": "Run the requested workspace regression inside the approved Docker sandbox.",
          "status": "awaiting_approval",
          "intent": "sandbox:execute_workspace_command",
          "result_summary": "",
          "capability_steps": [
            {
              "kind": "sandbox",
              "requires_approval": true,
              "note": "Needs operator approval before Docker-isolated execution.",
              "name": "execute_workspace_command"
            }
          ],
          "proposal_id": "ap-approve-1",
          "requires_approval": true,
          "tool_name": "execute_workspace_command",
          "execution_spec": {
            "executor": "pytest",
            "profile": "pytest",
            "runner_kind": "docker_isolated_runner",
            "isolation_level": "docker_local_isolated",
            "image_ref": "amadeus-thread0/sandbox-phase2:py312",
            "network_policy": "none",
            "workspace_root_kind": "runtime_owned",
            "argv": [
              "pytest",
              "-q",
              "tests/test_frontend_contract_sync.py"
            ],
            "cwd": "E:/runtime/workspaces/contract-demo",
            "allowed_roots": [
              "E:/runtime/workspaces/contract-demo"
            ],
            "timeout_s": 60,
            "writes_expected": false,
            "expected_artifacts": []
          },
          "execution_preview": {
            "executor": "pytest",
            "profile": "pytest",
            "runner_kind": "docker_isolated_runner",
            "isolation_level": "docker_local_isolated",
            "image_ref": "amadeus-thread0/sandbox-phase2:py312",
            "network_policy": "none",
            "workspace_root_kind": "runtime_owned",
            "argv": [
              "pytest",
              "-q",
              "tests/test_frontend_contract_sync.py"
            ],
            "cwd": "E:/runtime/workspaces/contract-demo",
            "allowed_roots": [
              "E:/runtime/workspaces/contract-demo"
            ],
            "timeout_s": 60,
            "writes_expected": false,
            "expected_artifacts": [],
            "summary": "Run the contract sync tests in the Docker-isolated sandbox after approval.",
            "requires_approval": true
          },
          "execution_result": {
            "run_id": "",
            "status": "not_started",
            "exit_code": null,
            "duration_ms": 0,
            "stdout_log_ref": "",
            "stderr_log_ref": "",
            "produced_artifacts": [],
            "error_summary": ""
          }
        }
      ],
      "execution_trace": [
        {
          "event": "approval_requested",
          "intent": "sandbox:execute_workspace_command",
          "status": "awaiting_approval",
          "requires_approval": true,
          "risk": "external_mutation",
          "origin": "counterpart_request",
          "proposal_id": "ap-approve-1"
        }
      ],
      "pending_approval": {
        "intent": "sandbox:execute_workspace_command",
        "status": "awaiting_approval",
        "requires_approval": true,
        "risk": "external_mutation",
        "origin": "counterpart_request",
        "proposal_id": "ap-approve-1",
        "tool_name": "execute_workspace_command",
        "execution_preview": {
          "executor": "pytest",
          "profile": "pytest",
          "runner_kind": "docker_isolated_runner",
          "isolation_level": "docker_local_isolated",
          "image_ref": "amadeus-thread0/sandbox-phase2:py312",
          "network_policy": "none",
          "workspace_root_kind": "runtime_owned",
          "argv": [
            "pytest",
            "-q",
            "tests/test_frontend_contract_sync.py"
          ],
          "cwd": "E:/runtime/workspaces/contract-demo",
          "allowed_roots": [
            "E:/runtime/workspaces/contract-demo"
          ],
          "timeout_s": 60,
          "writes_expected": false,
          "expected_artifacts": [],
          "summary": "Run the contract sync tests in the Docker-isolated sandbox after approval.",
          "requires_approval": true
        }
      }
    },
    "digital_body": {
      "constraints": [
        "human_approval_required",
        "network_policy_none"
      ],
      "action_channels": [
        "language",
        "structured_action",
        "tooling"
      ],
      "available_toolsets": [
        "filesystem",
        "sandbox"
      ],
      "active_surface": "approval_gate",
      "access_state": {
        "browser_session": "present",
        "block_reason": "waiting for approval",
        "granted_toolsets": [
          "filesystem",
          "sandbox"
        ],
        "requestable_access": [
          "workspace_execute",
          "human_approval"
        ],
        "filesystem_state": "workspace_available",
        "conditions": [
          "human_approval_required"
        ],
        "sandbox_mode": "restricted",
        "mode": "approval_pending",
        "pending_approval_count": 1,
        "cookie_state": "missing",
        "missing_access": [
          "workspace_execute"
        ],
        "network_access": "none",
        "account_state": "logged_out",
        "api_key_state": "missing",
        "quota_state": "unknown",
        "external_mutation_pending": true,
        "session_continuity": "stable",
        "session_expires_in_s": 0,
        "session_recovery_mode": "none",
        "access_acquire_proposals": [],
        "selected_access_proposal": {},
        "session_state": {
          "continuity": "stable",
          "expires_in_s": 0,
          "recovery_mode": "none",
          "retry_after_s": 0,
          "cooldown_scope": "",
          "browser_session": "present",
          "needs_recovery": false
        },
        "account_state_detail": {
          "browser_session": "present",
          "login_state": "logged_out",
          "cookie_state": "missing",
          "api_key_state": "missing",
          "account_available": false,
          "cookie_available": false,
          "api_key_available": false
        },
        "quota_state_detail": {
          "provider_state": "unknown",
          "retry_after_s": 0,
          "cooldown_scope": "",
          "available": true,
          "cooldown_active": false
        },
        "permission_state": {
          "pending_approval_count": 1,
          "external_mutation_pending": true,
          "missing_access": [
            "workspace_execute"
          ],
          "requestable_access": [
            "workspace_execute",
            "human_approval"
          ],
          "access_acquire_proposals": [],
          "selected_access_proposal": {},
          "resolved_grants": [],
          "pending_grants": [
            "workspace_execute"
          ],
          "completion_ratio": 0.0,
          "approval_state": "pending"
        },
        "sandbox_state": {
          "availability": "restricted",
          "allowed_roots": [
            "E:/runtime/workspaces/contract-demo"
          ],
          "execution_policy": "approval_required",
          "last_status": "awaiting_approval",
          "runner_kind": "docker_isolated_runner",
          "isolation_level": "docker_local_isolated",
          "image_ref": "amadeus-thread0/sandbox-phase2:py312",
          "network_policy": "none",
          "workspace_root_kind": "runtime_owned",
          "last_command_profile": "pytest",
          "last_exit_code": 0,
          "last_run_id": "ap-approve-1",
          "arbitrary_execution": false
        },
        "browser_runtime_state": {
          "availability": "available",
          "profile_root": "E:/runtime/browser/profiles/thread-demo",
          "context_status": "active",
          "active_page_id": "page-contract-demo",
          "active_tab_count": 1,
          "downloads_dir": "E:/runtime/browser/downloads/thread-demo",
          "last_action_status": "idle",
          "last_run_id": "ap-browser-contract-demo",
          "manual_takeover_required": false,
          "runner_kind": "playwright_persistent_context",
          "isolation_level": "persistent_profile_runtime"
        }
      },
      "perception_channels": [
        "dialogue",
        "scene"
      ],
      "world_surfaces": [
        "filesystem",
        "sandbox",
        "browser"
      ],
      "active_tools": [
        "execute_workspace_command"
      ],
      "resource_state": {
        "external_tool_count": 1,
        "executing_packet_count": 0,
        "behavior_queue_depth": 1,
        "completed_packet_count": 0,
        "queued_packet_count": 0,
        "pending_approval_count": 1,
        "blocked_packet_count": 0,
        "action_packet_count": 1,
        "artifact_continuity": "attached",
        "active_artifact_kind": "workspace",
        "active_artifact_ref": "E:/runtime/workspaces/contract-demo",
        "active_artifact_label": "contract-demo",
        "artifact_age_s": 0,
        "artifact_reacquisition_mode": "reuse_workspace_root",
        "artifact_carrier": "filesystem",
        "artifact_source_ref_ids": [],
        "preferred_source_ref_id": 0,
        "preferred_anchor_reason": "",
        "artifact_source_url": "",
        "artifact_source_query": "",
        "artifact_source_title": "",
        "artifact_source_tool_name": "",
        "workspace_root": "E:/runtime/workspaces/contract-demo",
        "browser_profile_id": "thread-demo",
        "browser_tab_id": "tab-contract-demo"
      }
    },
    "digital_body_consequence": {
      "kind": "access_request_pending",
      "requested_access": [
        "workspace_execute",
        "human_approval"
      ],
      "requested_help": true,
      "summary": "She already moved this step to the approval gate.",
      "primary_status": "awaiting_approval",
      "sandbox_state": {
        "availability": "restricted",
        "allowed_roots": [
          "E:/runtime/workspaces/contract-demo"
        ],
        "execution_policy": "approval_required",
        "last_status": "awaiting_approval",
        "runner_kind": "docker_isolated_runner",
        "isolation_level": "docker_local_isolated",
        "image_ref": "amadeus-thread0/sandbox-phase2:py312",
        "network_policy": "none",
        "workspace_root_kind": "runtime_owned",
        "last_command_profile": "pytest",
        "last_exit_code": 0,
        "last_run_id": "ap-approve-1",
        "arbitrary_execution": false
      },
      "browser_runtime_state": {
        "availability": "available",
        "profile_root": "E:/runtime/browser/profiles/thread-demo",
        "context_status": "active",
        "active_page_id": "page-contract-demo",
        "active_tab_count": 1,
        "downloads_dir": "E:/runtime/browser/downloads/thread-demo",
        "last_action_status": "idle",
        "last_run_id": "ap-browser-contract-demo",
        "manual_takeover_required": false,
        "runner_kind": "playwright_persistent_context",
        "isolation_level": "persistent_profile_runtime"
      },
      "workspace_root": "E:/runtime/workspaces/contract-demo",
      "workspace_root_kind": "runtime_owned",
      "sandbox_runner_kind": "docker_isolated_runner",
      "sandbox_isolation_level": "docker_local_isolated",
      "sandbox_image_ref": "amadeus-thread0/sandbox-phase2:py312",
      "sandbox_network_policy": "none"
    },
    "skills": {
      "installed": [
        {
          "skill_id": "source-ref-anchor-review",
          "name": "source-ref-anchor-review",
          "description": "Review saved source continuity before new search.",
          "version": "1.0.0",
          "kind": "authored_local",
          "source": "local",
          "status": "installed",
          "trust_tier": "repo_owned",
          "required_surfaces": [
            "source_ref"
          ],
          "allowed_tools": [
            "inspect_source_ref"
          ],
          "sandbox_profiles": [
            "workspace_read"
          ]
        }
      ],
      "matched": [
        {
          "skill_id": "source-ref-anchor-review",
          "name": "source-ref-anchor-review",
          "description": "Review saved source continuity before new search.",
          "version": "1.0.0",
          "kind": "authored_local",
          "source": "local",
          "status": "installed",
          "trust_tier": "repo_owned",
          "required_surfaces": [
            "source_ref"
          ],
          "allowed_tools": [
            "inspect_source_ref"
          ],
          "sandbox_profiles": [
            "workspace_read"
          ]
        }
      ],
      "active": [
        {
          "skill_id": "source-ref-anchor-review",
          "name": "source-ref-anchor-review",
          "description": "Review saved source continuity before new search.",
          "version": "1.0.0",
          "kind": "authored_local",
          "source": "local",
          "trust_tier": "repo_owned",
          "required_surfaces": [
            "source_ref"
          ],
          "allowed_tools": [
            "inspect_source_ref"
          ],
          "sandbox_profiles": [
            "workspace_read"
          ],
          "skill_excerpt": "Inspect the preferred saved source before searching again."
        }
      ],
      "manual_overrides": {
        "enabled": [],
        "disabled": [],
        "pinned": []
      },
      "pending_approval": {
        "proposal_id": "ap-skill-install-1",
        "operation": "install",
        "skill_id": "workspace-regression-triage",
        "resolved_version": "1.1.0",
        "source": "official_registry",
        "hash": "sha256:contract-demo",
        "requested_permissions": [
          "filesystem_read"
        ],
        "sandbox_profiles": [
          "workspace_read"
        ],
        "verification_summary": "registry metadata verified"
      }
    }
  },
  "meta": {
    "source": "cli"
  }
}
